README.rst
setup.py
ox_mon/__init__.py
ox_mon.egg-info/PKG-INFO
ox_mon.egg-info/SOURCES.txt
ox_mon.egg-info/dependency_links.txt
ox_mon.egg-info/entry_points.txt
ox_mon.egg-info/requires.txt
ox_mon.egg-info/top_level.txt
ox_mon/backup/__init__.py
ox_mon/backup/simple_backups.py
ox_mon/checking/__init__.py
ox_mon/checking/apt_checker.py
ox_mon/checking/clamav_checker.py
ox_mon/checking/disk_checker.py
ox_mon/checking/file_checker.py
ox_mon/checking/net_checker.py
ox_mon/checking/version_checker.py
ox_mon/common/__init__.py
ox_mon/common/configs.py
ox_mon/common/exceptions.py
ox_mon/common/interface.py
ox_mon/common/noters.py
ox_mon/common/stubs.py
ox_mon/misc/__init__.py
ox_mon/misc/cmds.py
ox_mon/triggers/__init__.py
ox_mon/triggers/file_triggers.py
ox_mon/ui/__init__.py
ox_mon/ui/cmd_line.py