Metadata-Version: 1.1
Name: ox-mon
Version: 0.2.15
Summary: Monitor status, security, and robustness of your machines.
Home-page: http://github.com/emin63/ox_mon
Author: Emin Martinian
Author-email: emin.martinian@gmail.com
License: MIT
Keywords: updating packages
Platform: UNKNOWN
Classifier: Development Status :: 3 - Alpha
Classifier: Intended Audience :: Developers
Classifier: Programming Language :: Python :: 3
